bitchute_dl/__init__.py
bitchute_dl/__main__.py
bitchute_dl-1.0.6.dist-info/LICENSE
bitchute_dl-1.0.6.dist-info/METADATA
bitchute_dl-1.0.6.dist-info/WHEEL
bitchute_dl-1.0.6.dist-info/entry_points.txt
bitchute_dl-1.0.6.dist-info/top_level.txt
bitchute_dl-1.0.6.dist-info/RECORD
