Metadata-Version: 2.1
Name: bitchute-dl
Version: 1.0.6
Summary: Download any BitChute video to your PC
Home-page: https://libersystems.com
Author: Matteljay
Author-email: matteljay@pm.me
License: MIT
Download-URL: https://github.com/Matteljay/bitchute-dl/releases
Keywords: bitchute,downloader,youtube-dl,video,archive
Platform: UNKNOWN
Classifier: Programming Language :: Python :: 3
Classifier: License :: OSI Approved :: MIT License
Classifier: Operating System :: OS Independent
Requires-Python: >=3.6
Requires-Dist: lxml (==4.5.0) ; python_version >= "2" and python_version < "3"
Requires-Dist: lxml ; python_version >= "3"
